quantnb/__init__.py
quantnb/core/PNL.py
quantnb/core/__init__.py
quantnb/core/backtester.old.py
quantnb/core/backtester.py
quantnb/core/base.py
quantnb/core/calculate_commission.py
quantnb/core/calculate_entry_price.py
quantnb/core/calculate_exit_price.py
quantnb/core/data_module.py
quantnb/core/enums.py
quantnb/core/from_signals.py
quantnb/core/from_trades.py
quantnb/core/helpers.py
quantnb/core/place_orders_on_ohlc.py
quantnb/core/specs_nb.py
quantnb/core/test.py
quantnb/core/trade_add_trade_to_active_trades.py
quantnb/core/trade_close_trade.py
quantnb/core/trade_create_new_trade.py
quantnb/core/trade_module.py
quantnb/core/trade_remove_from_active_trades.py
quantnb/core/trade_should_trade_close.py
quantnb/helpers/H_ticks_to_ranges.py
quantnb/helpers/S_calculate_metrics.py
quantnb/helpers/S_print_orders.py
quantnb/helpers/S_print_trades.py
quantnb/helpers/__init__.py
quantnb/helpers/analyze_trade_duration.py
quantnb/helpers/calculate_average_freq.py
quantnb/helpers/calculate_pf_stats.py
quantnb/helpers/calculate_risk_free.py
quantnb/helpers/get_average_trade_duration.py
quantnb/helpers/get_realized_pf_value.py
quantnb/helpers/plot_lines.py
quantnb/helpers/save_to_csv.py
quantnb/indicators/ATR.py
quantnb/indicators/EMA.py
quantnb/indicators/HMA.py
quantnb/indicators/I_donchian.py
quantnb/indicators/SMA.py
quantnb/indicators/__init__.py
quantnb/indicators/cross_above.py
quantnb/indicators/cross_below.py
quantnb/indicators/random_data.py
quantnb/indicators/supertrend.py
quantnb/lib/__init__.py
quantnb/lib/calculate_stats.py
quantnb/lib/convert_signal_to_markers.py
quantnb/lib/create_binance_dataframe.py
quantnb/lib/data_to_csv.py
quantnb/lib/fetch_binance_data.py
quantnb/lib/find_files.py
quantnb/lib/get_series_values.py
quantnb/lib/helpers.py
quantnb/lib/multiprocess.py
quantnb/lib/optimize.py
quantnb/lib/output_trades.py
quantnb/lib/plotting.py
quantnb/lib/qs.py
quantnb/lib/resample.py
quantnb/lib/time_manip.py
quantnb/strategies/S_MACD.py
quantnb-0.6.2.dist-info/METADATA
quantnb-0.6.2.dist-info/WHEEL
quantnb-0.6.2.dist-info/RECORD
